pq/__init__.py
pq/client.py
pq/config.py
pq/logging.py
pq/migrations/README
pq/migrations/__init__.py
pq/migrations/env.py
pq/migrations/script.py.mako
pq/migrations/versions/20260109T055839Z_476683af098d_initial_schema.py
pq/migrations/versions/20260109T063747Z_2483bec70083_add_client_id.py
pq/migrations/versions/__init__.py
pq/models.py
pq/priority.py
pq/registry.py
pq/serialization.py
pq/worker.py
python_pq-0.4.1.dist-info/WHEEL
python_pq-0.4.1.dist-info/entry_points.txt
python_pq-0.4.1.dist-info/METADATA
python_pq-0.4.1.dist-info/RECORD
