Metadata-Version: 2.3
Name: python-pq
Version: 0.4.1
Summary: Postgres-backed job queue for Python
Author: ricwo
Author-email: ricwo <r@cogram.com>
Requires-Dist: alembic>=1.17.2
Requires-Dist: click>=8.3.1
Requires-Dist: croniter>=6.0.0
Requires-Dist: dill>=0.4.0
Requires-Dist: loguru>=0.7.3
Requires-Dist: psycopg2-binary>=2.9.11
Requires-Dist: pydantic>=2.12.5
Requires-Dist: pydantic-settings>=2.12.0
Requires-Dist: sqlalchemy>=2.0.45
Requires-Dist: mkdocs-material>=9.7.1 ; extra == 'docs'
Requires-Dist: mkdocstrings[python]>=1.0.0 ; extra == 'docs'
Requires-Python: >=3.13, <3.15
Provides-Extra: docs
